velocitas_examples/seat-adjuster/AppManifest.json
velocitas_examples/seat-adjuster/Dockerfile
velocitas_examples/seat-adjuster/README.md
velocitas_examples/seat-adjuster/requirements-links.txt
velocitas_examples/seat-adjuster/requirements-velocitas.txt
velocitas_examples/seat-adjuster/requirements.in
velocitas_examples/seat-adjuster/requirements.txt
velocitas_examples/seat-adjuster/src/__init__.py
velocitas_examples/seat-adjuster/src/main.py
velocitas_examples/seat-adjuster/src/vapp.py
velocitas_examples/seat-adjuster/tests/__init__.py
velocitas_examples/seat-adjuster/tests/requirements.in
velocitas_examples/seat-adjuster/tests/requirements.txt
velocitas_examples/seat-adjuster/tests/integration/__init__.py
velocitas_examples/seat-adjuster/tests/integration/integration_test.py
velocitas_examples/seat-adjuster/tests/unit/__init__.py
velocitas_examples/seat-adjuster/tests/unit/test_run.py
velocitas_sdk/__init__.py
velocitas_sdk/base.py
velocitas_sdk/config.py
velocitas_sdk/model.py
velocitas_sdk/py.typed
velocitas_sdk/vehicle_app.py
velocitas_sdk/native/__init__.py
velocitas_sdk/native/locator.py
velocitas_sdk/native/middleware.py
velocitas_sdk/native/mqtt.py
velocitas_sdk/proto/broker_pb2.py
velocitas_sdk/proto/broker_pb2.pyi
velocitas_sdk/proto/broker_pb2_grpc.py
velocitas_sdk/proto/collector_pb2.py
velocitas_sdk/proto/collector_pb2.pyi
velocitas_sdk/proto/collector_pb2_grpc.py
velocitas_sdk/proto/types_pb2.py
velocitas_sdk/proto/types_pb2.pyi
velocitas_sdk/proto/types_pb2_grpc.py
velocitas_sdk/test/__init__.py
velocitas_sdk/test/databroker_testhelper.py
velocitas_sdk/test/inttesthelper.py
velocitas_sdk/test/mqtt_util.py
velocitas_sdk/util/__init__.py
velocitas_sdk/util/log.py
velocitas_sdk/vdb/__init__.py
velocitas_sdk/vdb/client.py
velocitas_sdk/vdb/reply.py
velocitas_sdk/vdb/subscriptions.py
velocitas_sdk/vdb/types.py
velocitas_sdk-0.15.6.dist-info/licenses/LICENSE
velocitas_sdk-0.15.6.dist-info/licenses/NOTICE-3RD-PARTY-CONTENT.md
velocitas_sdk-0.15.6.dist-info/licenses/NOTICE.md
velocitas_sdk-0.15.6.dist-info/METADATA
velocitas_sdk-0.15.6.dist-info/WHEEL
velocitas_sdk-0.15.6.dist-info/top_level.txt
velocitas_sdk-0.15.6.dist-info/RECORD
