Metadata-Version: 2.4
Name: velocitas_sdk
Version: 0.15.6
Summary: A Python SDK for Vehicle app
Home-page: https://github.com/eclipse-velocitas/vehicle-app-python-sdk
Classifier: Programming Language :: Python :: 3
Classifier: License :: OSI Approved :: Apache Software License
Classifier: Operating System :: OS Independent
License-File: LICENSE
License-File: NOTICE-3RD-PARTY-CONTENT.md
License-File: NOTICE.md
Requires-Dist: grpcio==1.64.1
Requires-Dist: protobuf==5.29.5
Requires-Dist: cloudevents==1.11.0
Requires-Dist: aiohttp==3.10.11
Requires-Dist: paho-mqtt==2.1.0
Requires-Dist: opentelemetry-distro==0.46b0
Requires-Dist: opentelemetry-instrumentation-logging==0.46b0
Requires-Dist: opentelemetry-sdk==1.25.0
Requires-Dist: opentelemetry-api==1.25.0
Provides-Extra: dev
Requires-Dist: protobuf; extra == "dev"
Requires-Dist: grpcio>=1.59.0; extra == "dev"
Requires-Dist: grpcio-tools; extra == "dev"
Requires-Dist: grpc-stubs; extra == "dev"
Requires-Dist: mypy-protobuf; extra == "dev"
Requires-Dist: apscheduler; extra == "dev"
Requires-Dist: Deprecated; extra == "dev"
Requires-Dist: types-Deprecated; extra == "dev"
Requires-Dist: pytest; extra == "dev"
Requires-Dist: pytest-asyncio; extra == "dev"
Requires-Dist: types-mock; extra == "dev"
Requires-Dist: pytest-cov; extra == "dev"
Requires-Dist: tox; extra == "dev"
Requires-Dist: pre-commit; extra == "dev"
Requires-Dist: mypy; extra == "dev"
Requires-Dist: pip-tools; extra == "dev"
Dynamic: classifier
Dynamic: description
Dynamic: description-content-type
Dynamic: home-page
Dynamic: license-file
Dynamic: provides-extra
Dynamic: requires-dist
Dynamic: summary
